django_mdeditor_v3-0.2.2.dist-info/licenses/LICENSE
mdeditor/__init__.py
mdeditor/configs.py
mdeditor/fields.py
mdeditor/urls.py
mdeditor/views.py
mdeditor/widgets.py
mdeditor/static/mdeditor/css/editormd.css
mdeditor/static/mdeditor/css/editormd.logo.css
mdeditor/static/mdeditor/css/editormd.logo.min.css
mdeditor/static/mdeditor/css/editormd.min.css
mdeditor/static/mdeditor/css/editormd.preview.css
mdeditor/static/mdeditor/css/editormd.preview.min.css
mdeditor/static/mdeditor/css/style.css
mdeditor/static/mdeditor/fonts/FontAwesome.otf
mdeditor/static/mdeditor/fonts/editormd-logo.eot
mdeditor/static/mdeditor/fonts/editormd-logo.svg
mdeditor/static/mdeditor/fonts/editormd-logo.ttf
mdeditor/static/mdeditor/fonts/editormd-logo.woff
mdeditor/static/mdeditor/fonts/fontawesome-webfont.eot
mdeditor/static/mdeditor/fonts/fontawesome-webfont.svg
mdeditor/static/mdeditor/fonts/fontawesome-webfont.ttf
mdeditor/static/mdeditor/fonts/fontawesome-webfont.woff
mdeditor/static/mdeditor/fonts/fontawesome-webfont.woff2
mdeditor/static/mdeditor/images/loading.gif
mdeditor/static/mdeditor/images/loading@2x.gif
mdeditor/static/mdeditor/images/loading@3x.gif
mdeditor/static/mdeditor/images/logos/editormd-favicon-16x16.ico
mdeditor/static/mdeditor/images/logos/editormd-favicon-24x24.ico
mdeditor/static/mdeditor/images/logos/editormd-favicon-32x32.ico
mdeditor/static/mdeditor/images/logos/editormd-favicon-48x48.ico
mdeditor/static/mdeditor/images/logos/editormd-favicon-64x64.ico
mdeditor/static/mdeditor/images/logos/editormd-logo-114x114.png
mdeditor/static/mdeditor/images/logos/editormd-logo-120x120.png
mdeditor/static/mdeditor/images/logos/editormd-logo-144x144.png
mdeditor/static/mdeditor/images/logos/editormd-logo-16x16.png
mdeditor/static/mdeditor/images/logos/editormd-logo-180x180.png
mdeditor/static/mdeditor/images/logos/editormd-logo-240x240.png
mdeditor/static/mdeditor/images/logos/editormd-logo-24x24.png
mdeditor/static/mdeditor/images/logos/editormd-logo-320x320.png
mdeditor/static/mdeditor/images/logos/editormd-logo-32x32.png
django_mdeditor_v3-0.2.2.dist-info/METADATA
django_mdeditor_v3-0.2.2.dist-info/WHEEL
django_mdeditor_v3-0.2.2.dist-info/top_level.txt
django_mdeditor_v3-0.2.2.dist-info/RECORD
